openkorpos_dic/__init__.py
openkorpos_dic/mecabrc
openkorpos_dic/openkorpos_dic.py
openkorpos_dic/version
openkorpos_dic/dicdir/LICENSE
openkorpos_dic/dicdir/README.md
openkorpos_dic/dicdir/char.bin
openkorpos_dic/dicdir/dicrc
openkorpos_dic/dicdir/left-id.def
openkorpos_dic/dicdir/matrix.bin
openkorpos_dic/dicdir/model.bin
openkorpos_dic/dicdir/pos-id.def
openkorpos_dic/dicdir/rewrite.def
openkorpos_dic/dicdir/right-id.def
openkorpos_dic/dicdir/sys.dic
openkorpos_dic/dicdir/unk.dic
openkorpos_dic-1.0.0.dist-info/LICENSE
openkorpos_dic-1.0.0.dist-info/METADATA
openkorpos_dic-1.0.0.dist-info/WHEEL
openkorpos_dic-1.0.0.dist-info/top_level.txt
openkorpos_dic-1.0.0.dist-info/RECORD
