Metadata-Version: 2.1
Name: openkorpos-dic
Version: 1.0.0
Summary: OpenKorPOS-dic packaged for Python
Home-page: https://github.com/NoUnique/openkorpos-dic-py
Author: Taehwan Yoo
Author-email: kofmap@gmail.com
Classifier: Programming Language :: Python :: 3
Classifier: Operating System :: OS Independent
Classifier: Natural Language :: Korean
License-File: LICENSE
